MANIFEST.in
setup.py
goodreads/__init__.py
goodreads/author.py
goodreads/book.py
goodreads/client.py
goodreads/comment.py
goodreads/event.py
goodreads/group.py
goodreads/owned_book.py
goodreads/request.py
goodreads/review.py
goodreads/session.py
goodreads/user.py
goodreads/user_status.py
goodreads.egg-info/PKG-INFO
goodreads.egg-info/SOURCES.txt
goodreads.egg-info/dependency_links.txt
goodreads.egg-info/requires.txt
goodreads.egg-info/top_level.txt