Metadata-Version: 1.0
Name: goodreads
Version: 0.2.0
Summary: Python wrapper for Goodreads API
Home-page: https://github.com/sefakilic/goodreads/
Author: Sefa Kilic
Author-email: sefakilic@gmail.com
License: MIT
Platform: UNKNOWN
